home_connect_async/__init__.py
home_connect_async/api.py
home_connect_async/appliance.py
home_connect_async/auth.py
home_connect_async/callback_registery.py
home_connect_async/common.py
home_connect_async/const.py
home_connect_async/homeconnect.py
home_connect_async-0.8.3.dist-info/METADATA
home_connect_async-0.8.3.dist-info/WHEEL
home_connect_async-0.8.3.dist-info/top_level.txt
home_connect_async-0.8.3.dist-info/RECORD
