Metadata-Version: 2.4
Name: home-connect-async
Version: 0.8.3
Summary: Async SDK for BSH Home Connect API
Home-page: https://github.com/ekutner/home-connect-async
Author: Eran Kutner
Author-email: eran@kutner.org
License: MIT
Keywords: HomeConnect,Home Connect,BSH,Async,SDK
Classifier: Development Status :: 5 - Production/Stable
Classifier: Intended Audience :: Developers
Classifier: Topic :: Software Development :: Build Tools
Classifier: License :: OSI Approved :: MIT License
Classifier: Programming Language :: Python :: 3
Classifier: Programming Language :: Python :: 3.9
Classifier: Programming Language :: Python :: 3.10
Requires-Dist: aiohttp
Requires-Dist: aiohttp-sse-client>=0.2.1
Requires-Dist: dataclasses-json>=0.5.6
Requires-Dist: oauth2-client>=1.2.1
Requires-Dist: charset_normalizer
Dynamic: author
Dynamic: author-email
Dynamic: classifier
Dynamic: home-page
Dynamic: keywords
Dynamic: license
Dynamic: requires-dist
Dynamic: summary
